__init__.py
pyggui/__init__.py
pyggui/__main__.py
pyggui/controller.py
pyggui/exceptions.py
pyggui/input.py
pyggui/main.py
pyggui/window.py
pyggui/client/__init__.py
pyggui/client/build.py
pyggui/client/cli.py
pyggui/client/make.py
pyggui/configure/__init__.py
pyggui/configure/asset_builder.py
pyggui/configure/build.py
pyggui/configure/pages.py
pyggui/defaults/__init__.py
pyggui/defaults/__welcome_page.py
pyggui/defaults/assets/__init__.py
pyggui/defaults/assets/fonts/__init__.py
pyggui/defaults/assets/fonts/retro_gaming.ttf
pyggui/defaults/structures/__init__.py
pyggui/defaults/structures/base/main.py
pyggui/defaults/structures/base/assets/.ignore
pyggui/defaults/structures/base/pages/__init__.py
pyggui/defaults/structures/base/pages/welcome_page.py
pyggui/gui/__init__.py
pyggui/gui/animation.py
pyggui/gui/bar.py
pyggui/gui/button.py
pyggui/gui/container.py
pyggui/gui/event_handler.py
pyggui/gui/grid.py
pyggui/gui/image.py
pyggui/gui/item.py
pyggui/gui/page.py
pyggui/gui/text.py
pyggui/helpers/__init__.py
pyggui/helpers/file_handling.py
pyggui/helpers/helpers.py
pyggui/helpers/stack.py
pyggui-0.0.1.dist-info/AUTHORS.rst
pyggui-0.0.1.dist-info/LICENSE
pyggui-0.0.1.dist-info/METADATA
pyggui-0.0.1.dist-info/WHEEL
pyggui-0.0.1.dist-info/entry_points.txt
pyggui-0.0.1.dist-info/top_level.txt
pyggui-0.0.1.dist-info/RECORD
