Metadata-Version: 2.1
Name: pyggui
Version: 0.0.1
Summary: Pygame project for simplifying page and menu creation while still leaving full controll
Home-page: https://github.com/15minutOdmora/python-pyggui
Author: Liam Mislej
Author-email: liammislej@gmail.com
License: MIT
Project-URL: Documentation, https://python-pyggui.readthedocs.io/
Project-URL: Changelog, https://python-pyggui.readthedocs.io/en/latest/changelog.html
Project-URL: Issue Tracker, https://github.com/15minutOdmora/python-pyggui/issues
Platform: UNKNOWN
Classifier: Development Status :: 5 - Production/Stable
Classifier: Intended Audience :: Developers
Classifier: License :: OSI Approved :: MIT License
Classifier: Operating System :: Unix
Classifier: Operating System :: POSIX
Classifier: Operating System :: Microsoft :: Windows
Classifier: Programming Language :: Python
Classifier: Programming Language :: Python :: 3
Classifier: Programming Language :: Python :: 3 :: Only
Classifier: Programming Language :: Python :: 3.6
Classifier: Programming Language :: Python :: 3.7
Classifier: Programming Language :: Python :: 3.8
Classifier: Programming Language :: Python :: 3.9
Classifier: Programming Language :: Python :: 3.10
Classifier: Programming Language :: Python :: Implementation :: CPython
Classifier: Programming Language :: Python :: Implementation :: PyPy
Classifier: Topic :: Utilities
Requires-Python: >=3.6
License-File: LICENSE
License-File: AUTHORS.rst
Requires-Dist: pygame (>2)
Requires-Dist: pyinstaller
